{"cameraMode":{"drawMode":0,"name":"Shaded","section":"Shading Mode"},"sceneLighting":true,"audioPlay":false,"sceneViewState":{"m_AlwaysRefresh":false,"showFog":true,"showSkybox":true,"showFlares":true,"showImageEffects":true,"showParticleSystems":true,"showVisualEffectGraphs":true,"m_FxEnabled":true},"in2DMode":false,"pivot":{"x":-66.43505859375,"y":13.12586784362793,"z":85.06925964355469},"rotation":{"x":-0.0602714978158474,"y":-0.02365122362971306,"z":0.0013946624239906669,"w":-0.9981362223625183},"size":83.46328735351563,"orthographic":false}